anonymous/__init__.py
anonx-0.0.0.dev1.dist-info/LICENSE
anonx-0.0.0.dev1.dist-info/METADATA
anonx-0.0.0.dev1.dist-info/WHEEL
anonx-0.0.0.dev1.dist-info/top_level.txt
anonx-0.0.0.dev1.dist-info/RECORD
