Metadata-Version: 2.1
Name: anonx
Version: 0.0.0.dev1
Summary: A python library with tools.
Home-page: https://github.com/anonxwallet/python-anonx
Author: Meheret Tesfaye Batu
Author-email: meherett@zoho.com
License: GPL-3.0
Keywords: anonymous,exchange,anonx
Platform: UNKNOWN
Classifier: Development Status :: 1 - Planning
Classifier: License :: OSI Approved :: GNU General Public License v3 (GPLv3)
Classifier: Programming Language :: Python :: 3.9
Classifier: Programming Language :: Python :: 3.10
Classifier: Programming Language :: Python :: 3.11
Classifier: Topic :: Software Development :: Libraries :: Python Modules
Requires-Python: >=3.6,<4
License-File: LICENSE
Provides-Extra: tests
Requires-Dist: pytest (<7,>=6.0.1) ; extra == 'tests'
Requires-Dist: pytest-cov (<3,>=2.10.1) ; extra == 'tests'
